MANIFEST.in
README.rst
setup.py
docs/HISTORY.txt
docs/LICENSE.GPL
docs/LICENSE.txt
ibme/__init__.py
ibme.persondirectory.egg-info/PKG-INFO
ibme.persondirectory.egg-info/SOURCES.txt
ibme.persondirectory.egg-info/dependency_links.txt
ibme.persondirectory.egg-info/entry_points.txt
ibme.persondirectory.egg-info/namespace_packages.txt
ibme.persondirectory.egg-info/not-zip-safe
ibme.persondirectory.egg-info/requires.txt
ibme.persondirectory.egg-info/top_level.txt
ibme/persondirectory/__init__.py
ibme/persondirectory/behaviors.py
ibme/persondirectory/catalog.py
ibme/persondirectory/configure.zcml
ibme/persondirectory/events.py
ibme/persondirectory/meta.zcml
ibme/persondirectory/overrides.zcml
ibme/persondirectory/setuphandlers.py
ibme/persondirectory/widget.py
ibme/persondirectory/browser/__init__.py
ibme/persondirectory/browser/configure.zcml
ibme/persondirectory/browser/directory.py
ibme/persondirectory/browser/pdir_directory_view.pt
ibme/persondirectory/browser/pdir_entry_fragment.pt
ibme/persondirectory/browser/pdir_entry_view.pt
ibme/persondirectory/models/__init__.py
ibme/persondirectory/models/pdir_directory.xml
ibme/persondirectory/models/pdir_entry.xml
ibme/persondirectory/profiles/default/ibme_persondirectory-default.txt
ibme/persondirectory/profiles/default/metadata.xml
ibme/persondirectory/profiles/default/propertiestool.xml
ibme/persondirectory/profiles/default/types.xml
ibme/persondirectory/profiles/default/types/pdir_directory.xml
ibme/persondirectory/profiles/default/types/pdir_entry.xml
ibme/persondirectory/tests/__init__.py
ibme/persondirectory/tests/base.py
ibme/persondirectory/tests/test_browser_directory.py
ibme/persondirectory/tests/test_catalog.py
ibme/persondirectory/tests/test_contenttypes.py
ibme/persondirectory/widget_templates/suggestion_input.pt