Metadata-Version: 1.1
Name: ibme.persondirectory
Version: 1.1
Summary: Directory of people
Home-page: http://shuttlethread.com
Author: Jamie Lentin
Author-email: jamie.lentin@shuttlethread.com
License: UNKNOWN
Keywords: plone person directory
Platform: UNKNOWN
Classifier: Framework :: Plone
Classifier: Programming Language :: Python
